clientry/__init__.py
clientry/base.py
clientry/errors.py
clientry/py.typed
clientry/types.py
clientry-2.0.0.dist-info/METADATA
clientry-2.0.0.dist-info/WHEEL
clientry-2.0.0.dist-info/RECORD
