Metadata-Version: 2.4
Name: clientry
Version: 2.0.0
Summary: A collection of code for clientry.
Project-URL: Homepage, https://github.com/gao-hongnan/clientry
Project-URL: Issues, https://github.com/gao-hongnan/clientry/issues
Author-email: GAO Hongnan <hongnangao@gmail.com>
Classifier: License :: OSI Approved :: Apache Software License
Classifier: Operating System :: OS Independent
Classifier: Programming Language :: Python :: 3
Classifier: Programming Language :: Python :: 3.12
Classifier: Programming Language :: Python :: 3.13
Requires-Python: >=3.12
Requires-Dist: httpx>=0.28.1
Requires-Dist: pydantic-settings>=2.10.1
Requires-Dist: pydantic>=2.11.7
Requires-Dist: rich>=13.0.0
Requires-Dist: tenacity>=9.1.2
